pypdf/__init__.py
pypdf/_cmap.py
pypdf/_encryption.py
pypdf/_merger.py
pypdf/_page.py
pypdf/_page_labels.py
pypdf/_protocols.py
pypdf/_reader.py
pypdf/_utils.py
pypdf/_version.py
pypdf/_writer.py
pypdf/constants.py
pypdf/errors.py
pypdf/filters.py
pypdf/pagerange.py
pypdf/papersizes.py
pypdf/py.typed
pypdf/types.py
pypdf/xmp.py
pypdf/_codecs/__init__.py
pypdf/_codecs/adobe_glyphs.py
pypdf/_codecs/pdfdoc.py
pypdf/_codecs/std.py
pypdf/_codecs/symbol.py
pypdf/_codecs/zapfding.py
pypdf/_crypt_providers/__init__.py
pypdf/_crypt_providers/_base.py
pypdf/_crypt_providers/_cryptography.py
pypdf/_crypt_providers/_fallback.py
pypdf/_crypt_providers/_pycryptodome.py
pypdf/_text_extraction/__init__.py
pypdf/annotations/__init__.py
pypdf/annotations/_base.py
pypdf/annotations/_markup_annotations.py
pypdf/annotations/_non_markup_annotations.py
pypdf/generic/__init__.py
pypdf/generic/_base.py
pypdf/generic/_data_structures.py
pypdf/generic/_fit.py
pypdf/generic/_outline.py
pypdf/generic/_rectangle.py
pypdf/generic/_utils.py
pypdf-3.15.3.dist-info/LICENSE
pypdf-3.15.3.dist-info/WHEEL
pypdf-3.15.3.dist-info/METADATA
pypdf-3.15.3.dist-info/RECORD
