Metadata-Version: 2.1
Name: pypdf
Version: 3.15.3
Summary: A pure-python PDF library capable of splitting, merging, cropping, and transforming PDF files
Author-email: Mathieu Fenniak <biziqe@mathieu.fenniak.net>
Maintainer-email: Martin Thoma <info@martin-thoma.de>
Requires-Python: >=3.6
Classifier: Development Status :: 5 - Production/Stable
Classifier: Intended Audience :: Developers
Classifier: License :: OSI Approved :: BSD License
Classifier: Programming Language :: Python :: 3
Classifier: Programming Language :: Python :: 3.6
Classifier: Programming Language :: Python :: 3.7
Classifier: Programming Language :: Python :: 3.8
Classifier: Programming Language :: Python :: 3.9
Classifier: Programming Language :: Python :: 3.10
Classifier: Programming Language :: Python :: 3.11
Classifier: Programming Language :: Python :: 3.12
Classifier: Operating System :: OS Independent
Classifier: Topic :: Software Development :: Libraries :: Python Modules
Classifier: Typing :: Typed
Requires-Dist: typing_extensions >= 3.10.0.0; python_version < '3.10'
Requires-Dist: dataclasses; python_version < '3.7'
Requires-Dist: cryptography ; extra == "crypto" and ( python_version >= '3.7')
Requires-Dist: PyCryptodome ; extra == "crypto" and ( python_version == '3.6')
Requires-Dist: black ; extra == "dev"
Requires-Dist: pip-tools ; extra == "dev"
Requires-Dist: pre-commit<2.18.0 ; extra == "dev"
Requires-Dist: pytest-cov ; extra == "dev"
Requires-Dist: pytest-socket ; extra == "dev"
Requires-Dist: pytest-timeout ; extra == "dev"
Requires-Dist: flit ; extra == "dev"
Requires-Dist: wheel ; extra == "dev"
Requires-Dist: sphinx ; extra == "docs"
Requires-Dist: sphinx_rtd_theme ; extra == "docs"
Requires-Dist: myst_parser ; extra == "docs"
Requires-Dist: cryptography ; extra == "full" and ( python_version >= '3.7')
Requires-Dist: PyCryptodome ; extra == "full" and ( python_version == '3.6')
Requires-Dist: Pillow>=8.0.0 ; extra == "full"
Requires-Dist: Pillow>=8.0.0 ; extra == "image"
Project-URL: Bug Reports, https://github.com/py-pdf/pypdf/issues
Project-URL: Changelog, https://pypdf.readthedocs.io/en/latest/meta/CHANGELOG.html
Project-URL: Documentation, https://pypdf.readthedocs.io/en/latest/
Project-URL: Source, https://github.com/py-pdf/pypdf
Provides-Extra: crypto
Provides-Extra: dev
Provides-Extra: docs
Provides-Extra: full
Provides-Extra: image
